flair/__init__.py
flair/data.py
flair/data_fetcher.py
flair/datasets/__init__.py
flair/datasets/base.py
flair/datasets/biomedical.py
flair/datasets/document_classification.py
flair/datasets/sequence_labeling.py
flair/datasets/text_image.py
flair/datasets/text_text.py
flair/datasets/treebanks.py
flair/embeddings/__init__.py
flair/embeddings/base.py
flair/embeddings/document.py
flair/embeddings/image.py
flair/embeddings/legacy.py
flair/embeddings/token.py
flair/file_utils.py
flair/hyperparameter/__init__.py
flair/hyperparameter/param_selection.py
flair/hyperparameter/parameter.py
flair/inference_utils.py
flair/models/__init__.py
flair/models/language_model.py
flair/models/sequence_tagger_model.py
flair/models/similarity_learning_model.py
flair/models/text_classification_model.py
flair/models/text_regression_model.py
flair/nn.py
flair/optim.py
flair/samplers.py
flair/tokenization.py
flair/trainers/__init__.py
flair/trainers/language_model_trainer.py
flair/trainers/trainer.py
flair/training_utils.py
flair/visual/__init__.py
flair/visual/activations.py
flair/visual/manifold.py
flair/visual/ner_html.py
flair/visual/training_curves.py
pd3f_flair-0.6.0.1.dist-info/LICENSE
pd3f_flair-0.6.0.1.dist-info/WHEEL
pd3f_flair-0.6.0.1.dist-info/METADATA
pd3f_flair-0.6.0.1.dist-info/RECORD
