Metadata-Version: 2.1
Name: pd3f-flair
Version: 0.6.0.1
Summary: Flair's language models without unnecessary dependencies
License: MIT
Author: Alan Akbik
Author-email: alan.akbik@gmail.com
Requires-Python: >=3.6
Classifier: License :: OSI Approved :: MIT License
Classifier: Programming Language :: Python :: 3
Classifier: Programming Language :: Python :: 3.6
Classifier: Programming Language :: Python :: 3.7
Classifier: Programming Language :: Python :: 3.8
Requires-Dist: deprecated
Requires-Dist: numpy
Requires-Dist: requests
Requires-Dist: torch
Requires-Dist: tqdm
